whitebox_plugin_gps_simulator/pyproject.toml
whitebox_plugin_gps_simulator/__init__.py
whitebox_plugin_gps_simulator/gps_simulation.csv
whitebox_plugin_gps_simulator/static/whitebox_plugin_gps_simulator/whitebox_plugin_gps_simulator.js
whitebox_plugin_gps_simulator/templates/whitebox_plugin_gps_simulator/whitebox_plugin_gps_simulator.html
whitebox_plugin_gps_simulator/whitebox_plugin_gps_simulator.py
whitebox_test_plugin_gps_simulator/__init__.py
whitebox_test_plugin_gps_simulator/test_whitebox_plugin_gps_simulator.py
whitebox_test_plugin_gps_simulator/test_whitebox_plugin_gps_simulator_integration.py
whitebox_plugin_gps_simulator-0.1.13.dist-info/LICENSE
whitebox_plugin_gps_simulator-0.1.13.dist-info/METADATA
whitebox_plugin_gps_simulator-0.1.13.dist-info/WHEEL
whitebox_plugin_gps_simulator-0.1.13.dist-info/RECORD
